[
  {
    "month": 0,
    "dateAsked": "4/14",
    "questionAsked": "What is the year before 1 AD called?",
    "questionAnswer": "1 B.C."
  },
  {
    "month": 0,
    "dateAsked": "4/18",
    "questionAsked": "The word \u0022alphabet\u0022 comes from the the word \u0022alpha\u0022 and what other one?",
    "questionAnswer": "Beta"
  },
  {
    "month": 0,
    "dateAsked": "4/20",
    "questionAsked": "[Player Name]! C\u0027mon, man, help me here!",
    "questionAnswer": "Three"
  },
  {
    "month": 0,
    "dateAsked": "4/23",
    "questionAsked": "What\u0027s this ergonomic bubble she\u0027s asking about!?",
    "questionAnswer": "Tulip mania"
  },
  {
    "month": 0,
    "dateAsked": "4/25",
    "questionAsked": "... what\u0027s it called when you gain more muscle after getting sore through excercise?",
    "questionAnswer": "Overcompensation"
  },
  {
    "month": 0,
    "dateAsked": "4/26",
    "questionAsked": "I don\u0027t think I\u0027ve heard of any of these!",
    "questionAnswer": "Marriage numbers"
  },
  {
    "month": 0,
    "dateAsked": "4/30",
    "questionAsked": "What is the greatest canyon in the solar system?",
    "questionAnswer": "Valles Marineris"
  },
  {
    "month": 1,
    "dateAsked": "5/7",
    "questionAsked": "Do you know how Soseki Natsume translated the English phrase \u0022I love you\u0022 into Japanese?",
    "questionAnswer": "The moon is beautiful, isn\u0027t it?"
  },
  {
    "month": 1,
    "dateAsked": "5/9",
    "questionAsked": "What is it called when muscles grow after excercise?",
    "questionAnswer": "Overcompensation"
  },
  {
    "month": 1,
    "dateAsked": "5/9",
    "questionAsked": "What is the year before 1 A.D. called?",
    "questionAnswer": "1 B.C."
  },
  {
    "month": 1,
    "dateAsked": "5/10",
    "questionAsked": "Which of these types of numbers does not exist?",
    "questionAnswer": "Marriage numbers"
  },
  {
    "month": 1,
    "dateAsked": "5/10",
    "questionAsked": "Who translated \u0022I love you\u0022 as \u0022The moon is beautiful, isn\u0027t it\u0022?",
    "questionAnswer": "Soseki Natsume"
  },
  {
    "month": 1,
    "dateAsked": "5/11",
    "questionAsked": "Who said \u0022As soon as laws are necessary for men, they are no longer fit for freedom\u0022?",
    "questionAnswer": "Pythagoras"
  },
  {
    "month": 1,
    "dateAsked": "5/11",
    "questionAsked": "Which of the following is the highest mountain in the solar system?",
    "questionAnswer": "Olympus Mons"
  },
  {
    "month": 1,
    "dateAsked": "5/26",
    "questionAsked": "Something about laborers?",
    "questionAnswer": "Attendance logs"
  },
  {
    "month": 2,
    "dateAsked": "6/8",
    "questionAsked": "What sport is \u0022heikin-dai\u0022?",
    "questionAnswer": "Balance Beam"
  },
  {
    "month": 2,
    "dateAsked": "6/13",
    "questionAsked": "What kind of excercise is a sprint classified as?",
    "questionAnswer": "Anaerobics"
  },
  {
    "month": 2,
    "dateAsked": "6/15",
    "questionAsked": "Sorry, [Player Name], tell me what morale is!?",
    "questionAnswer": "Cheerfulness of a group"
  },
  {
    "month": 2,
    "dateAsked": "6/20",
    "questionAsked": "What period did Japan first implement bonus pay?",
    "questionAnswer": "Meiji"
  },
  {
    "month": 2,
    "dateAsked": "6/27",
    "questionAsked": "Answer this: What is identity?",
    "questionAnswer": "Individuality"
  },
  {
    "month": 2,
    "dateAsked": "6/30",
    "questionAsked": "Which one of these is the name of a real river?",
    "questionAnswer": "Pis Pis River"
  },
  {
    "month": 3,
    "dateAsked": "7/4",
    "questionAsked": "You gotta help me out?",
    "questionAnswer": "Pascal"
  },
  {
    "month": 3,
    "dateAsked": "7/7",
    "questionAsked": "What is the beginning of \u0022Gakumon no Susume\u0022 a reference to?",
    "questionAnswer": "The U.S. Declaration of Independence"
  },
  {
    "month": 3,
    "dateAsked": "7/13",
    "questionAsked": "What is the medical term for brainfreeze!?",
    "questionAnswer": "Sphenopalatine ganglioneuralgia"
  },
  {
    "month": 3,
    "dateAsked": "7/14",
    "questionAsked": "Which famous Heian-ero monk famously used a wrong version of the \u0022\u5FDC\u0022 kanji?",
    "questionAnswer": "Kuukai"
  },
  {
    "month": 3,
    "dateAsked": "7/15",
    "questionAsked": "Which line can a typhoon never cross?",
    "questionAnswer": "The equator"
  },
  {
    "month": 3,
    "dateAsked": "7/16",
    "questionAsked": "... what makes the king of hearts look different from the other kings in a standard deck of cards?",
    "questionAnswer": "He has no mustache"
  },
  {
    "month": 3,
    "dateAsked": "7/19",
    "questionAsked": "What is morale?",
    "questionAnswer": "Cheerfulness in a group"
  },
  {
    "month": 3,
    "dateAsked": "7/19",
    "questionAsked": "What sport is \u0022heikin-dai\u0022?",
    "questionAnswer": "Balance Beam"
  },
  {
    "month": 3,
    "dateAsked": "7/20",
    "questionAsked": "It is said, \u0022Even Kobo made mistakes in writing.\u0022 Which kanji did he make a mistake on?",
    "questionAnswer": "\u5FDC (The first one)"
  },
  {
    "month": 3,
    "dateAsked": "7/20",
    "questionAsked": "In which period did Japan first implement bonus pay?",
    "questionAnswer": "Meiji"
  },
  {
    "month": 3,
    "dateAsked": "7/21",
    "questionAsked": "Which king in a deck of cards is missing a mustache?",
    "questionAnswer": "King of Hearts"
  },
  {
    "month": 3,
    "dateAsked": "7/21",
    "questionAsked": "Who said this: \u0022Man is but a reed, the most feeble thing in nature; but he is a thinking reed\u0022?",
    "questionAnswer": "Pascal"
  },
  {
    "month": 3,
    "dateAsked": "7/22",
    "questionAsked": "Which one of these is the name of real river?",
    "questionAnswer": "Pis Pis River"
  },
  {
    "month": 3,
    "dateAsked": "7/22",
    "questionAsked": "What is the beginning of \u0022Gakumon no Susume\u0022 a reference to?/",
    "questionAnswer": "The U.S. Declaration of Independence"
  },
  {
    "month": 4,
    "dateAsked": "8/28",
    "questionAsked": "NOTE: Study with Justice to be asked.\nIs it the male or female platypus that has the poison claws?",
    "questionAnswer": "Male"
  },
  {
    "month": 4,
    "dateAsked": "8/29",
    "questionAsked": "NOTE: Study with Justice to be asked.\nDid it rain the day that we worked on my art homework?",
    "questionAnswer": "It stopped raining by then"
  },
  {
    "month": 5,
    "dateAsked": "9/1",
    "questionAsked": "\u0022Venison\u0022 is the meat of what animal?",
    "questionAnswer": "All of the above"
  },
  {
    "month": 5,
    "dateAsked": "9/5",
    "questionAsked": "Which of the following is a kigo for fall?",
    "questionAnswer": "Brisk"
  },
  {
    "month": 5,
    "dateAsked": "9/17",
    "questionAsked": "How short was history\u0027s shortest war?",
    "questionAnswer": "40 minutes"
  },
  {
    "month": 5,
    "dateAsked": "9/20",
    "questionAsked": "What do you call somebody who\u0027s between ninety and one hundred years old?",
    "questionAnswer": "A nonagenarian"
  },
  {
    "month": 5,
    "dateAsked": "9/28",
    "questionAsked": "Do you know the answer?",
    "questionAnswer": "Throat"
  },
  {
    "month": 6,
    "dateAsked": "10/4",
    "questionAsked": "Which of these sports also uses an anchor?",
    "questionAnswer": "Tug-of-War"
  },
  {
    "month": 6,
    "dateAsked": "10/5",
    "questionAsked": "Do you know the answer, [Player Name]?",
    "questionAnswer": "The right edge"
  },
  {
    "month": 6,
    "dateAsked": "10/8",
    "questionAsked": "Tell me what bird\u0027s name means \u0022coward\u0022 in English!",
    "questionAnswer": "Chicken"
  },
  {
    "month": 6,
    "dateAsked": "10/11",
    "questionAsked": "What did Napoleon have invented?",
    "questionAnswer": "Glass jars"
  },
  {
    "month": 6,
    "dateAsked": "10/12",
    "questionAsked": "Do you know what vegetables was used to make the first jack-o\u0027-latern?",
    "questionAnswer": "Turnips"
  },
  {
    "month": 6,
    "dateAsked": "10/13",
    "questionAsked": "What kind of fish was I just talking about?",
    "questionAnswer": "Ojisan"
  },
  {
    "month": 6,
    "dateAsked": "10/14",
    "questionAsked": "What part of the body contains the \u0022Adam\u0027s apple\u0022?",
    "questionAnswer": "Throat"
  },
  {
    "month": 6,
    "dateAsked": "10/14",
    "questionAsked": "Where would you find Japan on a map made in a foreign country?",
    "questionAnswer": "The right edge"
  },
  {
    "month": 6,
    "dateAsked": "10/15",
    "questionAsked": "How short was history\u0027s shortest war?",
    "questionAnswer": "40 minutes"
  },
  {
    "month": 6,
    "dateAsked": "10/15",
    "questionAsked": "\u0022Venison\u0022 is the meat of what animal?",
    "questionAnswer": "All of the above"
  },
  {
    "month": 6,
    "dateAsked": "10/17",
    "questionAsked": "What is the Japanese name for \u0022panda\u0022?",
    "questionAnswer": "Black and white bears"
  },
  {
    "month": 6,
    "dateAsked": "10/17",
    "questionAsked": "Which bird is falsely known for being cowardly in the English phrase to stick one\u0027s head in the sand",
    "questionAnswer": "Ostrich"
  },
  {
    "month": 6,
    "dateAsked": "10/18",
    "questionAsked": "What was the name of the Wasan textbook that came out in the Edo period?",
    "questionAnswer": "Math Girl"
  },
  {
    "month": 6,
    "dateAsked": "10/18",
    "questionAsked": "What did Napoleon have invented?",
    "questionAnswer": "Glass jars"
  },
  {
    "month": 6,
    "dateAsked": "10/19",
    "questionAsked": "Which season is the adjective \u0022brisk\u0022 a kigo for?",
    "questionAnswer": "Fall"
  },
  {
    "month": 6,
    "dateAsked": "10/19",
    "questionAsked": "What is \u0022Dragon\u0027s Blood\u0022?",
    "questionAnswer": "Plant resin"
  },
  {
    "month": 7,
    "dateAsked": "11/1",
    "questionAsked": "Tell me what the \u0022figure\u0022 in \u0022figure skating\u0022 refer to!",
    "questionAnswer": "Geometric shapes"
  },
  {
    "month": 7,
    "dateAsked": "11/4",
    "questionAsked": "Sorry [Player Name], I have no idea",
    "questionAnswer": "A cuckoo"
  },
  {
    "month": 7,
    "dateAsked": "11/7",
    "questionAsked": "Which country do you think the South Pole belongs to?",
    "questionAnswer": "No country"
  },
  {
    "month": 7,
    "dateAsked": "11/11",
    "questionAsked": "What desert is the Welwitschia from?",
    "questionAnswer": "Namib"
  },
  {
    "month": 7,
    "dateAsked": "11/17",
    "questionAsked": "Is that even in a textbook? The roots of \u0022bridal\u0022? What..?",
    "questionAnswer": "Bride ale"
  },
  {
    "month": 7,
    "dateAsked": "11/22",
    "questionAsked": "Do you know what an \u0022atlast\u0022 is?",
    "questionAnswer": "A book of maps"
  },
  {
    "month": 7,
    "dateAsked": "11/24",
    "questionAsked": "0, 1, 2, 3, 5, 8, 13... What is this sequence called?",
    "questionAnswer": "Fibonacci sequence"
  },
  {
    "month": 7,
    "dateAsked": "11/25",
    "questionAsked": "There are over 130 ancient pyramids in Egypt, but do you know who\u0027s buried in the biggest one?",
    "questionAnswer": "Khufu"
  },
  {
    "month": 7,
    "dateAsked": "11/26",
    "questionAsked": "Which of these is considered a \u0022rice cake\u0022?",
    "questionAnswer": "Mochi"
  },
  {
    "month": 7,
    "dateAsked": "11/28",
    "questionAsked": "What does French food stem from?",
    "questionAnswer": "Italian food"
  },
  {
    "month": 7,
    "dateAsked": "11/28",
    "questionAsked": "What does the \u0022figure\u0022 in \u0022figure saking\u0022 refer to?",
    "questionAnswer": "Geometric shapes"
  },
  {
    "month": 7,
    "dateAsked": "11/29",
    "questionAsked": "Who is buried in the biggest pyramid in Egypt?",
    "questionAnswer": "Khufu"
  },
  {
    "month": 7,
    "dateAsked": "11/29",
    "questionAsked": "What is a book of maps called?",
    "questionAnswer": "Atlas"
  },
  {
    "month": 7,
    "dateAsked": "11/30",
    "questionAsked": "What word has the words \u0022bride ale\u0022 as its roots?",
    "questionAnswer": "Bridal"
  },
  {
    "month": 7,
    "dateAsked": "11/30",
    "questionAsked": "What kind of bird is a \u0022kanko-dori\u0022?",
    "questionAnswer": "A cuckoo"
  },
  {
    "month": 8,
    "dateAsked": "12/1",
    "questionAsked": "Which country does the South Pole belong to?",
    "questionAnswer": "No country"
  },
  {
    "month": 8,
    "dateAsked": "12/1",
    "questionAsked": "0, 1, 1, 2, 3, 5, 8, 13... What is this sequence called?",
    "questionAnswer": "The Fibonacci sequence"
  },
  {
    "month": 8,
    "dateAsked": "12/2",
    "questionAsked": "What desert is the Welwitschia found in?",
    "questionAnswer": "Namib"
  },
  {
    "month": 8,
    "dateAsked": "12/2",
    "questionAsked": "Which of these is considered a \u0022rice cake\u0022?",
    "questionAnswer": "Mochi"
  },
  {
    "month": 8,
    "dateAsked": "12/9",
    "questionAsked": "Do you know what color a fuzzy-wuzzy polar bear\u0027s fur really is?",
    "questionAnswer": "Transparent"
  },
  {
    "month": 8,
    "dateAsked": "12/10",
    "questionAsked": "What determines whether a hair grows curly or straight?",
    "questionAnswer": "The cross-section"
  },
  {
    "month": 8,
    "dateAsked": "12/17",
    "questionAsked": "Huh? What? I wasn\u0027t listening... [Player Name]-kun, help!",
    "questionAnswer": "Compassion makes you look better"
  },
  {
    "month": 8,
    "dateAsked": "12/21",
    "questionAsked": "[Player Name], will you tell me if you know the answer?",
    "questionAnswer": "VII"
  },
  {
    "month": 9,
    "dateAsked": "1/10",
    "questionAsked": "Tell me, what are you supposed to put on top of a kagami mochi?",
    "questionAnswer": "An orange"
  },
  {
    "month": 9,
    "dateAsked": "1/14",
    "questionAsked": "\u0022Toso\u0022 is a traditional drink for the new year, but what does that name mean?",
    "questionAnswer": "Bury the demons"
  },
  {
    "month": 9,
    "dateAsked": "1/19",
    "questionAsked": "In the Thai and Vietnamese zodiacs, which animal is used in the place of the rabbit?",
    "questionAnswer": "Cat"
  },
  {
    "month": 9,
    "dateAsked": "1/25",
    "questionAsked": "European snow in spring...? Do you know, [Player Name]-kun?",
    "questionAnswer": "Red"
  },
  {
    "month": 9,
    "dateAsked": "1/30",
    "questionAsked": "What\u0027s the next unit of measurement up from a terabyte?",
    "questionAnswer": "Petabyte"
  },
  {
    "month": 10,
    "dateAsked": "2/1",
    "questionAsked": "What color were the pyramids originally?",
    "questionAnswer": "White"
  },
  {
    "month": 10,
    "dateAsked": "2/6",
    "questionAsked": "The word \u0022alphabet\u0022 comes from the words \u0022alpha\u0022 and what other one?",
    "questionAnswer": "Beta"
  },
  {
    "month": 10,
    "dateAsked": "2/6",
    "questionAsked": "How was the theory that the pyramids were built by slaves disproven?",
    "questionAnswer": "Attendance logs"
  },
  {
    "month": 10,
    "dateAsked": "2/7",
    "questionAsked": "What drink name means \u0022bury demons\u0022?",
    "questionAnswer": "Toso"
  },
  {
    "month": 10,
    "dateAsked": "2/7",
    "questionAsked": "What is the medical term for brainfreeze?",
    "questionAnswer": "Sphenopalatine ganglioneuralgia"
  },
  {
    "month": 10,
    "dateAsked": "2/8",
    "questionAsked": "What is the Japanese zodiac equivalent to the \u0022cat\u0022 in the Thai and Vietnamese zodiacs?",
    "questionAnswer": "Rabbit"
  },
  {
    "month": 10,
    "dateAsked": "2/8",
    "questionAsked": "What vegetable was used to make the first jack-o\u0027-laterns?",
    "questionAnswer": "Turnips"
  },
  {
    "month": 10,
    "dateAsked": "2/9",
    "questionAsked": "What color were the pyramids when they were first built?",
    "questionAnswer": "White"
  },
  {
    "month": 10,
    "dateAsked": "2/9",
    "questionAsked": "What gets mixed with snow in Europe that sometimes causes it to turn red?",
    "questionAnswer": "The Sahara Desert sand"
  }
]
